.testr.conf
ADOPTERS.md
AUTHORS
CHANGES.rst
CODE_OF_CONDUCT.md
CONTRIBUTING.md
LICENSE
README.rst
pyproject.toml
requirements.txt
setup.cfg
setup.py
test-requirements.txt
tox.ini
.github/CODEOWNERS
.github/workflows/ci.yml
doc/source/changelog.rst
doc/source/conf.py
doc/source/git_stacktrace.rst
doc/source/index.rst
doc/source/python_api.rst
git_stacktrace/__init__.py
git_stacktrace/api.py
git_stacktrace/cmd.py
git_stacktrace/git.py
git_stacktrace/parse_trace.py
git_stacktrace/result.py
git_stacktrace/server.py
git_stacktrace.egg-info/PKG-INFO
git_stacktrace.egg-info/SOURCES.txt
git_stacktrace.egg-info/dependency_links.txt
git_stacktrace.egg-info/entry_points.txt
git_stacktrace.egg-info/not-zip-safe
git_stacktrace.egg-info/pbr.json
git_stacktrace.egg-info/requires.txt
git_stacktrace.egg-info/top_level.txt
git_stacktrace/templates/messages.html
git_stacktrace/templates/page.html
git_stacktrace/tests/__init__.py
git_stacktrace/tests/base.py
git_stacktrace/tests/test_api.py
git_stacktrace/tests/test_git.py
git_stacktrace/tests/test_parse_trace.py
git_stacktrace/tests/test_result.py
git_stacktrace/tests/test_server.py
git_stacktrace/tests/examples/java1.trace
git_stacktrace/tests/examples/java2.trace
git_stacktrace/tests/examples/java3.trace
git_stacktrace/tests/examples/java4.trace
git_stacktrace/tests/examples/javascript1.trace
git_stacktrace/tests/examples/javascript2.trace
git_stacktrace/tests/examples/javascript3.trace
git_stacktrace/tests/examples/javascript4.trace
git_stacktrace/tests/examples/javascript5.trace
git_stacktrace/tests/examples/python1.trace
git_stacktrace/tests/examples/python2.trace
git_stacktrace/tests/examples/python3.trace
git_stacktrace/tests/examples/python4.trace
git_stacktrace/tests/examples/python5.trace
git_stacktrace/tests/examples/python6.trace
git_stacktrace/tests/examples/python7.trace
git_stacktrace/tests/examples/python8.trace