Metadata-Version: 1.1
Name: git-stacktrace
Version: 1.0.0
Summary: git-blame for stacktraces
Home-page: https://github.com/pinterest/git-stacktrace
Author: Joe Gordon
Author-email: UNKNOWN
License: Apache License (2.0)
Platform: UNKNOWN
Classifier: Programming Language :: Python :: 3
Classifier: Programming Language :: Python :: 3.6
Classifier: Programming Language :: Python :: 3.7
Classifier: Programming Language :: Python :: 3.8
Classifier: Intended Audience :: Developers
Classifier: Operating System :: OS Independent
Classifier: License :: OSI Approved :: Apache Software License
